extpickle/__init__.py
extpickle/extpickle.py
extpickle-1.20160617.170648.dist-info/DESCRIPTION.rst
extpickle-1.20160617.170648.dist-info/METADATA
extpickle-1.20160617.170648.dist-info/RECORD
extpickle-1.20160617.170648.dist-info/WHEEL
extpickle-1.20160617.170648.dist-info/metadata.json
extpickle-1.20160617.170648.dist-info/pbr.json
extpickle-1.20160617.170648.dist-info/top_level.txt
